q_galore_torch/__init__.py
q_galore_torch/q_galore_adamw8bit.py
q_galore_torch/q_galore_adamw8bit_simulate.py
q_galore_torch/q_galore_projector.py
q_galore_torch/q_galore_projector_simulate.py
q_galore_torch-1.0.dist-info/LICENSE
q_galore_torch-1.0.dist-info/METADATA
q_galore_torch-1.0.dist-info/WHEEL
q_galore_torch-1.0.dist-info/top_level.txt
q_galore_torch-1.0.dist-info/RECORD
